calzone_display/__init__.py
calzone_display/_core.abi3.so
calzone_display-0.5.0.dist-info/COPYING.LESSER
calzone_display-0.5.0.dist-info/LICENSE
calzone_display-0.5.0.dist-info/METADATA
calzone_display-0.5.0.dist-info/WHEEL
calzone_display-0.5.0.dist-info/top_level.txt
calzone_display-0.5.0.dist-info/RECORD
