Metadata-Version: 2.4
Name: calzone-display
Version: 0.5.0
Summary: A display extension for Calzone (CALorimeter ZONE)
Author-email: Valentin Niess <valentin.niess@gmail.com>
License: LGPLv3
Project-URL: source, https://github.com/niess/calzone-display
Keywords: Python,Monte Carlo,Geant4,Display
Classifier: Intended Audience :: Science/Research
Classifier: Topic :: Scientific/Engineering :: Physics
Requires-Python: >=3.7.0
License-File: LICENSE
License-File: COPYING.LESSER
Requires-Dist: calzone>=0.4.0
Requires-Dist: numpy>=1.6.0
Dynamic: license-file
